{"type":"FeatureCollection","features":[{"type":"Feature","properties":{"occurrences":"7","theuri":"http://fr.dbpedia.org/resource/Angleterre","name":"Angleterre"},"geometry":{"type":"Point","coordinates":[-0.16666699945926666,51.5]}},{"type":"Feature","properties":{"occurrences":"3","theuri":"http://fr.dbpedia.org/resource/Espagne","name":"Espagne"},"geometry":{"type":"Point","coordinates":[-3.700000047683716,40.43330001831055]}},{"type":"Feature","properties":{"occurrences":"3","theuri":"http://fr.dbpedia.org/resource/Italie","name":"Italie"},"geometry":{"type":"Point","coordinates":[12.48330020904541,41.88330078125]}},{"type":"Feature","properties":{"occurrences":"2","theuri":"http://fr.dbpedia.org/resource/Malte","name":"Malte"},"geometry":{"type":"Point","coordinates":[14.51669979095459,35.900001525878906]}},{"type":"Feature","properties":{"occurrences":"1","theuri":"http://fr.dbpedia.org/resource/Nîmes","name":"Nîmes"},"geometry":{"type":"Point","coordinates":[4.36083,43.8378]}},{"type":"Feature","properties":{"occurrences":"1","theuri":"http://fr.dbpedia.org/resource/Brest","name":"Brest"},"geometry":{"type":"Point","coordinates":[-4.48556,48.3908]}},{"type":"Feature","properties":{"occurrences":"1","theuri":"http://fr.dbpedia.org/resource/Rue_de_Monceau","name":"rue de Monceau"},"geometry":{"type":"Point","coordinates":[2.31127,48.878]}},{"type":"Feature","properties":{"occurrences":"1","theuri":"http://fr.dbpedia.org/resource/Hongrie","name":"Hongrie"},"geometry":{"type":"Point","coordinates":[19.25,47.5]}},{"type":"Feature","properties":{"occurrences":"1","theuri":"http://fr.dbpedia.org/resource/Berlin","name":"Berlin"}},{"type":"Feature","properties":{"occurrences":"3","theuri":"http://fr.dbpedia.org/resource/Versailles","name":"Versailles"},"geometry":{"type":"Point","coordinates":[2.135,48.8053]}},{"type":"Feature","properties":{"occurrences":"3","theuri":"http://fr.dbpedia.org/resource/Europe","name":"Europe"}},{"type":"Feature","properties":{"occurrences":"1","theuri":"http://fr.dbpedia.org/resource/Château_de_Gourville","name":"château de Gourville"},"geometry":{"type":"Point","coordinates":[-0.0133333,45.8281]}},{"type":"Feature","properties":{"occurrences":"2","theuri":"http://fr.dbpedia.org/resource/Israël","name":"Israël"},"geometry":{"type":"Point","coordinates":[35.145301818847656,31.62529945373535]}},{"type":"Feature","properties":{"occurrences":"1","theuri":"http://fr.dbpedia.org/resource/Munich","name":"Munich"},"geometry":{"type":"Point","coordinates":[11.575,48.15]}},{"type":"Feature","properties":{"occurrences":"1","theuri":"http://fr.dbpedia.org/resource/Lyon","name":"Lyon"},"geometry":{"type":"Point","coordinates":[4.84222,45.7597]}},{"type":"Feature","properties":{"occurrences":"1","theuri":"http://fr.dbpedia.org/resource/Poitiers","name":"Poitiers"},"geometry":{"type":"Point","coordinates":[0.336112,46.5819]}},{"type":"Feature","properties":{"occurrences":"1","theuri":"http://fr.dbpedia.org/resource/Rue_de_Varenne","name":"rue de Varenne"},"geometry":{"type":"Point","coordinates":[2.32205,48.8544]}},{"type":"Feature","properties":{"occurrences":"2","theuri":"http://fr.dbpedia.org/resource/Chine","name":"Chine"},"geometry":{"type":"Point","coordinates":[103.08300018310547,32.79999923706055]}},{"type":"Feature","properties":{"occurrences":"1","theuri":"http://fr.dbpedia.org/resource/Nantes","name":"Nantes"},"geometry":{"type":"Point","coordinates":[-1.55278,47.2181]}},{"type":"Feature","properties":{"occurrences":"1","theuri":"http://fr.dbpedia.org/resource/Danemark","name":"Danemark"},"geometry":{"type":"Point","coordinates":[12.566699981689453,55.71670150756836]}},{"type":"Feature","properties":{"occurrences":"1","theuri":"http://fr.dbpedia.org/resource/Rennes","name":"Rennes"},"geometry":{"type":"Point","coordinates":[-1.67944,48.1147]}},{"type":"Feature","properties":{"occurrences":"1","theuri":"http://fr.dbpedia.org/resource/Amiens","name":"Amiens"},"geometry":{"type":"Point","coordinates":[2.29574,49.8943]}},{"type":"Feature","properties":{"occurrences":"7","theuri":"http://fr.dbpedia.org/resource/Orléans","name":"Orléans"},"geometry":{"type":"Point","coordinates":[1.909,47.9025]}},{"type":"Feature","properties":{"occurrences":"2","theuri":"http://fr.dbpedia.org/resource/Tours","name":"Tours"},"geometry":{"type":"Point","coordinates":[0.689167,47.3936]}},{"type":"Feature","properties":{"occurrences":"2","theuri":"http://fr.dbpedia.org/resource/Autriche","name":"Autriche"},"geometry":{"type":"Point","coordinates":[16.350000381469727,48.20000076293945]}},{"type":"Feature","properties":{"occurrences":"1","theuri":"http://fr.dbpedia.org/resource/Serbie","name":"Serbie"},"geometry":{"type":"Point","coordinates":[20.38330078125,44.79999923706055]}},{"type":"Feature","properties":{"occurrences":"31","theuri":"http://fr.dbpedia.org/resource/France","name":"France"},"geometry":{"type":"Point","coordinates":[2.3264999389648438,48.86669921875]}},{"type":"Feature","properties":{"occurrences":"5","theuri":"http://fr.dbpedia.org/resource/Allemagne","name":"Allemagne"},"geometry":{"type":"Point","coordinates":[13.41670036315918,52.516700744628906]}},{"type":"Feature","properties":{"occurrences":"2","theuri":"http://fr.dbpedia.org/resource/Cholet","name":"Cholet"},"geometry":{"type":"Point","coordinates":[-0.878333,47.06]}},{"type":"Feature","properties":{"occurrences":"1","theuri":"http://fr.dbpedia.org/resource/Château_de_Blois","name":"château de Blois"},"geometry":{"type":"Point","coordinates":[1.331,47.5855]}},{"type":"Feature","properties":{"occurrences":"2","theuri":"http://fr.dbpedia.org/resource/Suède","name":"Suède"}},{"type":"Feature","properties":{"occurrences":"1","theuri":"http://fr.dbpedia.org/resource/Nice","name":"Nice"},"geometry":{"type":"Point","coordinates":[7.27141,43.6959]}},{"type":"Feature","properties":{"occurrences":"1","theuri":"http://fr.dbpedia.org/resource/Reims","name":"Reims"},"geometry":{"type":"Point","coordinates":[4.03472,49.2628]}},{"type":"Feature","properties":{"occurrences":"2","theuri":"http://fr.dbpedia.org/resource/Rome","name":"Rome"},"geometry":{"type":"Point","coordinates":[12.4866,41.8887]}},{"type":"Feature","properties":{"occurrences":"2","theuri":"http://fr.dbpedia.org/resource/Londres","name":"Londres"},"geometry":{"type":"Point","coordinates":[-0.07857,51.5049]}},{"type":"Feature","properties":{"occurrences":"115","theuri":"http://fr.dbpedia.org/resource/Paris","name":"Paris"},"geometry":{"type":"Point","coordinates":[2.35183,48.8566]}},{"type":"Feature","properties":{"occurrences":"4","theuri":"http://fr.dbpedia.org/resource/Turquie","name":"Turquie"},"geometry":{"type":"Point","coordinates":[35.66669845581055,39.16669845581055]}},{"type":"Feature","properties":{"occurrences":"1","theuri":"http://fr.dbpedia.org/resource/Roumanie","name":"Roumanie"},"geometry":{"type":"Point","coordinates":[25.510000228881836,46.09000015258789]}},{"type":"Feature","properties":{"occurrences":"1","theuri":"http://fr.dbpedia.org/resource/Dunkerque","name":"Dunkerque"},"geometry":{"type":"Point","coordinates":[2.3775,51.0383]}},{"type":"Feature","properties":{"occurrences":"2","theuri":"http://fr.dbpedia.org/resource/Grèce","name":"Grèce"},"geometry":{"type":"Point","coordinates":[23.700000762939453,38.0]}},{"type":"Feature","properties":{"occurrences":"2","theuri":"http://fr.dbpedia.org/resource/Caen","name":"Caen"},"geometry":{"type":"Point","coordinates":[-0.370556,49.1822]}},{"type":"Feature","properties":{"occurrences":"1","theuri":"http://fr.dbpedia.org/resource/Beauvais","name":"Beauvais"},"geometry":{"type":"Point","coordinates":[2.0952,49.4303]}}]}
